tsln/__init__.py
tsln/py.typed
tsln/types.py
tsln/utils.py
tsln/core/__init__.py
tsln/core/analyzer.py
tsln/core/decoder.py
tsln/core/encoder.py
tsln/core/schema.py
tsln-1.0.0.dist-info/licenses/LICENSE
tsln-1.0.0.dist-info/METADATA
tsln-1.0.0.dist-info/WHEEL
tsln-1.0.0.dist-info/top_level.txt
tsln-1.0.0.dist-info/RECORD
