Metadata-Version: 2.4
Name: tsln
Version: 1.0.0
Summary: Time-Series Lean Notation - 74% token reduction for LLMs
Author-email: Turboline Team <dev@turboline.ai>
License: MIT
Project-URL: Homepage, https://github.com/turboline-ai/tsln-python
Project-URL: Documentation, https://github.com/turboline-ai/tsln-python#readme
Project-URL: Repository, https://github.com/turboline-ai/tsln-python
Project-URL: Issues, https://github.com/turboline-ai/tsln-python/issues
Keywords: tsln,time-series,compression,llm,tokens,ai,data-serialization
Classifier: Development Status :: 5 - Production/Stable
Classifier: Intended Audience :: Developers
Classifier: License :: OSI Approved :: MIT License
Classifier: Programming Language :: Python :: 3
Classifier: Programming Language :: Python :: 3.8
Classifier: Programming Language :: Python :: 3.9
Classifier: Programming Language :: Python :: 3.10
Classifier: Programming Language :: Python :: 3.11
Classifier: Programming Language :: Python :: 3.12
Classifier: Topic :: Software Development :: Libraries
Classifier: Topic :: Scientific/Engineering
Classifier: Topic :: Text Processing
Requires-Python: >=3.8
License-File: LICENSE
Requires-Dist: python-dateutil>=2.8.2
Provides-Extra: dev
Requires-Dist: pytest>=7.4.0; extra == "dev"
Requires-Dist: pytest-cov>=4.1.0; extra == "dev"
Requires-Dist: pytest-benchmark>=4.0.0; extra == "dev"
Requires-Dist: hypothesis>=6.82.0; extra == "dev"
Requires-Dist: black>=23.7.0; extra == "dev"
Requires-Dist: mypy>=1.4.1; extra == "dev"
Requires-Dist: ruff>=0.0.280; extra == "dev"
Provides-Extra: numpy
Requires-Dist: numpy>=1.20.0; extra == "numpy"
Provides-Extra: pandas
Requires-Dist: pandas>=1.3.0; extra == "pandas"
Dynamic: license-file
